meta_ads_mcp/__init__.py
meta_ads_mcp/__main__.py
meta_ads_mcp/core/__init__.py
meta_ads_mcp/core/accounts.py
meta_ads_mcp/core/ads.py
meta_ads_mcp/core/ads_library.py
meta_ads_mcp/core/adsets.py
meta_ads_mcp/core/api.py
meta_ads_mcp/core/auth.py
meta_ads_mcp/core/authentication.py
meta_ads_mcp/core/budget_schedules.py
meta_ads_mcp/core/callback_server.py
meta_ads_mcp/core/campaigns.py
meta_ads_mcp/core/http_auth_integration.py
meta_ads_mcp/core/insights.py
meta_ads_mcp/core/pipeboard_auth.py
meta_ads_mcp/core/resources.py
meta_ads_mcp/core/server.py
meta_ads_mcp/core/utils.py
meta_ads_mcp_local-0.4.5.dist-info/METADATA
meta_ads_mcp_local-0.4.5.dist-info/WHEEL
meta_ads_mcp_local-0.4.5.dist-info/entry_points.txt
meta_ads_mcp_local-0.4.5.dist-info/licenses/LICENSE
meta_ads_mcp_local-0.4.5.dist-info/RECORD
