Metadata-Version: 2.4
Name: meta-ads-mcp-local
Version: 0.4.5
Summary: Model Calling Protocol (MCP) plugin for interacting with Meta Ads API (Fork with HTTPS support)
Project-URL: Homepage, https://github.com/nictuku/meta-ads-mcp
Project-URL: Bug Tracker, https://github.com/nictuku/meta-ads-mcp/issues
Author-email: Yves Junqueira <yves.junqueira@gmail.com>, Fork Maintainer <fork@example.com>
License: MIT
License-File: LICENSE
Keywords: ads,api,claude,facebook,https,mcp,meta,oauth
Classifier: License :: OSI Approved :: MIT License
Classifier: Operating System :: OS Independent
Classifier: Programming Language :: Python :: 3
Requires-Python: >=3.10
Requires-Dist: httpx>=0.26.0
Requires-Dist: mcp[cli]>=1.9.0
Requires-Dist: pathlib>=1.0.1
Requires-Dist: pillow>=10.0.0
Requires-Dist: python-dateutil>=2.8.2
Requires-Dist: python-dotenv>=1.1.0
Requires-Dist: requests>=2.32.3
